egytech_api/__init__.py
egytech_api/core.py
egytech_api/models.py
egytech_api/tests.py
egytech_api-1.0.2.dist-info/METADATA
egytech_api-1.0.2.dist-info/WHEEL
egytech_api-1.0.2.dist-info/licenses/LICENSE
egytech_api-1.0.2.dist-info/RECORD
