Metadata-Version: 2.3
Name: egytech_api
Version: 1.0.2
Summary: A Python API Wrapper for the EgyTech.FYI API
Project-URL: Documentation, https://abdulrahman-mustafa.gitbook.io/egytech-fyi-python-wrapper
Project-URL: Source Code, https://github.com/Abdulrahman-Mustafa-Abdulrahman/egytech-api
Author-email: Abdulrahman Mustafa Abdulrahman <abdulrahman.m.khaled@outlook.com>
License: MIT License
License-File: LICENSE
Keywords: api,egytech,egytech api,egytech.fyi,wrapper
Classifier: Development Status :: 3 - Alpha
Classifier: Framework :: Pydantic
Classifier: Framework :: Pydantic :: 2
Classifier: Intended Audience :: Science/Research
Classifier: License :: OSI Approved :: MIT License
Classifier: Natural Language :: English
Classifier: Operating System :: OS Independent
Classifier: Programming Language :: Python :: 3.11
Requires-Python: >=3.11
Requires-Dist: httpx
Requires-Dist: pandas
Requires-Dist: pydantic==2.7.3
Requires-Dist: tomli
Requires-Dist: xlsxwriter
